xtb_trading/__init__.py
xtb_trading/main.py
xtb_trading-0.1.0.dist-info/METADATA
xtb_trading-0.1.0.dist-info/WHEEL
xtb_trading-0.1.0.dist-info/RECORD
